{
  "collection_timestamp": "2026-04-20T17:34:36+09:00",
  "source_stats": {
    "AI타임스": {
      "fetched": 0,
      "ai_matched": 0,
      "kept": 0,
      "error": "FeedFetchError"
    },
    "ZDNet Korea": {
      "fetched": 0,
      "ai_matched": 0,
      "kept": 0,
      "error": "FeedFetchError"
    },
    "전자신문": {
      "fetched": 0,
      "ai_matched": 0,
      "kept": 0,
      "error": "FeedFetchError"
    },
    "연합뉴스": {
      "fetched": 0,
      "ai_matched": 0,
      "kept": 0,
      "error": "FeedFetchError"
    },
    "매일경제": {
      "fetched": 0,
      "ai_matched": 0,
      "kept": 0,
      "error": "FeedFetchError"
    },
    "한겨레": {
      "fetched": 0,
      "ai_matched": 0,
      "kept": 0,
      "error": "FeedFetchError"
    }
  },
  "articles": []
}